mifa/__cli__.py
mifa/__init__.py
mifa-0.1.0.dist-info/entry_points.txt
mifa-0.1.0.dist-info/LICENSE
mifa-0.1.0.dist-info/WHEEL
mifa-0.1.0.dist-info/METADATA
mifa-0.1.0.dist-info/RECORD
