Metadata-Version: 2.1
Name: mifa
Version: 0.1.0
Summary: mitmproxy for android
License: MIT
Author: kin9-0rz
Author-email: kin9-0rz@outlook.com
Requires-Python: >=3.10,<4.0
Classifier: License :: OSI Approved :: MIT License
Classifier: Programming Language :: Python :: 3
Classifier: Programming Language :: Python :: 3.10
Classifier: Programming Language :: Python :: 3.11
Requires-Dist: click (>=8.1.3,<9.0.0)
Requires-Dist: psutil (>=5.9.4,<6.0.0)
Requires-Dist: rich (>=12.6.0,<13.0.0)
Requires-Dist: toml (>=0.10.2,<0.11.0)
